{"id":"DQgk05LhwfE2jLn3Km2TK","title":"Table","vault":{"fsPath":"vault"},"type":"note","desc":"A generic data structure.","links":[{"type":"wiki","from":{"fname":"lang.luau.types.table","id":"DQgk05LhwfE2jLn3Km2TK","vaultName":"vault"},"value":"lang.luau.library.table","alias":"lang.luau.library.table","position":{"start":{"line":2,"column":151,"offset":151},"end":{"line":2,"column":178,"offset":178},"indent":[]},"xvault":false,"sameFile":false,"to":{"fname":"lang.luau.library.table"}},{"type":"wiki","from":{"fname":"lang.luau.types.table","id":"DQgk05LhwfE2jLn3Km2TK","vaultName":"vault"},"value":"lang.luau.globals.pairs","alias":"lang.luau.globals.pairs","position":{"start":{"line":2,"column":213,"offset":213},"end":{"line":2,"column":240,"offset":240},"indent":[]},"xvault":false,"sameFile":false,"to":{"fname":"lang.luau.globals.pairs"}},{"type":"wiki","from":{"fname":"lang.luau.types.table","id":"DQgk05LhwfE2jLn3Km2TK","vaultName":"vault"},"value":"lang.luau.globals.ipairs","alias":"lang.luau.globals.ipairs","position":{"start":{"line":2,"column":245,"offset":245},"end":{"line":2,"column":273,"offset":273},"indent":[]},"xvault":false,"sameFile":false,"to":{"fname":"lang.luau.globals.ipairs"}},{"type":"wiki","from":{"fname":"lang.luau.types.table","id":"DQgk05LhwfE2jLn3Km2TK","vaultName":"vault"},"value":"lang.luau.metatable","alias":"lang.luau.metatable","position":{"start":{"line":8,"column":78,"offset":787},"end":{"line":8,"column":101,"offset":810},"indent":[]},"xvault":false,"sameFile":false,"to":{"fname":"lang.luau.metatable"}}],"anchors":{"examples":{"type":"header","text":"Examples","value":"examples","line":16,"column":0,"depth":2},"array":{"type":"header","text":"Array","value":"array","line":17,"column":0,"depth":3},"dictionaryobject":{"type":"header","text":"Dictionary/Object","value":"dictionaryobject","line":23,"column":0,"depth":3},"hybrid":{"type":"header","text":"Hybrid","value":"hybrid","line":38,"column":0,"depth":3}},"fname":"lang.luau.types.table","updated":1639690313836,"created":1639689370154,"parent":"8GeyH2ChnV7ijTpdkZX1b","children":[],"data":{},"contentHash":"6cb24e0dc7266eeb46655419dba5a015","custom":{}}
